{
  "_comment": "資源法股票池設定檔 — 修改此檔案即可更新股票池，無需改動程式碼",
  "_version": "1.0",
  "_updated": "2026-04-13",

  "watchlist": {
    "_comment": "固定自選股：5-10檔，每次執行均納入，不受 V4/V12 排名限制",
    "symbols": [
      "2330",
      "2317",
      "2454",
      "2308",
      "2382"
    ],
    "max_count": 10,
    "always_include_in_v12": true
  },

  "universe": {
    "_comment": "完整股票池：V4 每小時掃描 TOP20，V12 盤後全掃約 150 檔",
    "symbols": [
      "3030", "3706", "8096", "2313", "4958",
      "2330", "2317", "2454", "2308", "2382", "2303", "3711", "2412", "2357", "3231",
      "2379", "3008", "2395", "3045", "2327", "2408", "2377", "6669", "2301", "3034",
      "2345", "2474", "3037", "4938", "3443", "2353", "2324", "2603", "2609", "1513",
      "3293", "3680", "3529", "3131", "5274", "6223", "6805", "3017", "3324", "6515",
      "3661", "3583", "6139", "3035", "1560", "8299", "3558", "6187", "3406", "3217",
      "6176", "6415", "6206", "8069", "3264", "5269", "2360", "6271", "3189", "6438",
      "8358", "6231", "2449", "8016", "6679", "3374", "3014", "3211",
      "6213", "2404", "2480", "3596", "6202", "5443", "5347", "5483", "6147",
      "8046", "2368", "2383", "6269", "5469", "5351",
      "4909", "8050", "6153", "6505", "1802", "3708", "8213", "1325",
      "2344", "6239", "3260", "4967", "6414", "2337",
      "3551", "2436", "2375", "2492", "2456", "3229", "6173", "3533",
      "3491", "2367", "6285", "6190",
      "3062", "2419", "2314", "3305", "3105", "2312", "8086",
      "3081", "2455", "6442", "3163", "4979", "3363", "6451",
      "3450", "4908", "4977", "3234",
      "1711", "1727", "2489", "3060", "3498", "3535", "3580", "3587",
      "3665", "4749", "4989", "6217", "6290", "6418", "6443", "6470", "6542",
      "6546", "6706", "6831", "6861", "6877", "8028", "8111"
    ]
  },

  "settings": {
    "lookback_days": 250,
    "intraday_runs_per_day": 5,
    "intraday_top_n": 20,
    "postmarket_full_scan": true,
    "finmind_rate_limit_sec": 0.5,
    "yahoo_fallback_enabled": true,
    "data_source_priority": ["finmind", "yahoo"]
  }
}
