{
  "market": "TW",
  "top20": [
    {
      "score": 93.0,
      "pvo": 45.21,
      "vri": 58.0,
      "slope_z": 2.83,
      "slope": 12.663,
      "action": "強力買進",
      "signal": "基準-強勢+量爆",
      "combo_key": "基準-強勢",
      "close": 533.0,
      "atr": 18.62,
      "pos_weight": 0.195,
      "symbol": "4966",
      "regime": "偏多震盪",
      "rank": 1
    },
    {
      "score": 91.15,
      "pvo": 53.06,
      "vri": 66.4,
      "slope_z": 2.27,
      "slope": 10.671,
      "action": "強力買進",
      "signal": "基準-強勢+量爆",
      "combo_key": "基準-強勢",
      "close": 321.5,
      "atr": 9.6,
      "pos_weight": 0.195,
      "symbol": "2382",
      "regime": "偏多震盪",
      "rank": 2
    },
    {
      "score": 86.74,
      "pvo": 25.51,
      "vri": 55.4,
      "slope_z": 2.0,
      "slope": 8.014,
      "action": "強力買進",
      "signal": "基準-強勢+放量",
      "combo_key": "基準-強勢",
      "close": 62.0,
      "atr": 2.72,
      "pos_weight": 0.165,
      "symbol": "2303",
      "regime": "偏多震盪",
      "rank": 3
    },
    {
      "score": 85.41,
      "pvo": 23.4,
      "vri": 56.0,
      "slope_z": 1.96,
      "slope": 8.639,
      "action": "強力買進",
      "signal": "基準-強勢+量爆",
      "combo_key": "基準-強勢",
      "close": 83.0,
      "atr": 2.72,
      "pos_weight": 0.195,
      "symbol": "3706",
      "regime": "偏多震盪",
      "rank": 4
    },
    {
      "score": 82.28,
      "pvo": 36.08,
      "vri": 63.3,
      "slope_z": 1.16,
      "slope": 18.129,
      "action": "買進",
      "signal": "基準-持有+量爆",
      "combo_key": "基準-持有",
      "close": 303.0,
      "atr": 17.46,
      "pos_weight": 0.169,
      "symbol": "3030",
      "regime": "偏多震盪",
      "rank": 5
    },
    {
      "score": 73.59,
      "pvo": 10.67,
      "vri": 66.8,
      "slope_z": 1.28,
      "slope": 20.729,
      "action": "買進",
      "signal": "基準-強勢",
      "combo_key": "基準-強勢",
      "close": 265.0,
      "atr": 16.6,
      "pos_weight": 0.15,
      "symbol": "4958",
      "regime": "偏多震盪",
      "rank": 6
    },
    {
      "score": 73.36,
      "pvo": -0.45,
      "vri": 46.0,
      "slope_z": 1.94,
      "slope": 7.509,
      "action": "觀察",
      "signal": "基準-強勢",
      "combo_key": "基準-強勢",
      "close": 1575.0,
      "atr": 64.47,
      "pos_weight": 0.15,
      "symbol": "2454",
      "regime": "偏多震盪",
      "rank": 7
    },
    {
      "score": 72.68,
      "pvo": 6.02,
      "vri": 53.4,
      "slope_z": 1.46,
      "slope": 6.299,
      "action": "買進",
      "signal": "基準-強勢+放量",
      "combo_key": "基準-強勢",
      "close": 135.0,
      "atr": 4.2,
      "pos_weight": 0.165,
      "symbol": "3231",
      "regime": "偏多震盪",
      "rank": 8
    },
    {
      "score": 70.16,
      "pvo": 4.83,
      "vri": 56.2,
      "slope_z": 1.22,
      "slope": 13.163,
      "action": "買進",
      "signal": "基準-強勢",
      "combo_key": "基準-強勢",
      "close": 2665.0,
      "atr": 152.33,
      "pos_weight": 0.15,
      "symbol": "3443",
      "regime": "偏多震盪",
      "rank": 9
    },
    {
      "score": 69.22,
      "pvo": -1.14,
      "vri": 63.5,
      "slope_z": 1.45,
      "slope": 17.627,
      "action": "觀察",
      "signal": "基準-強勢",
      "combo_key": "基準-強勢",
      "close": 1735.0,
      "atr": 87.15,
      "pos_weight": 0.15,
      "symbol": "2308",
      "regime": "偏多震盪",
      "rank": 10
    },
    {
      "score": 68.8,
      "pvo": -5.85,
      "vri": 50.1,
      "slope_z": 1.57,
      "slope": 10.806,
      "action": "觀察",
      "signal": "基準-強勢",
      "combo_key": "基準-強勢",
      "close": 3025.0,
      "atr": 176.04,
      "pos_weight": 0.15,
      "symbol": "3661",
      "regime": "偏多震盪",
      "rank": 11
    },
    {
      "score": 68.13,
      "pvo": -7.08,
      "vri": 58.3,
      "slope_z": 1.53,
      "slope": 7.817,
      "action": "觀察",
      "signal": "基準-強勢",
      "combo_key": "基準-強勢",
      "close": 2000.0,
      "atr": 51.93,
      "pos_weight": 0.15,
      "symbol": "2330",
      "regime": "偏多震盪",
      "rank": 12
    },
    {
      "score": 66.44,
      "pvo": 4.58,
      "vri": 61.9,
      "slope_z": 0.77,
      "slope": 11.18,
      "action": "買進",
      "signal": "基準-持有+放量",
      "combo_key": "基準-持有",
      "close": 12580.0,
      "atr": 726.62,
      "pos_weight": 0.143,
      "symbol": "5274",
      "regime": "偏多震盪",
      "rank": 13
    },
    {
      "score": 66.39,
      "pvo": -5.06,
      "vri": 63.2,
      "slope_z": 1.24,
      "slope": 10.542,
      "action": "觀察",
      "signal": "基準-強勢",
      "combo_key": "基準-強勢",
      "close": 1835.0,
      "atr": 103.54,
      "pos_weight": 0.15,
      "symbol": "2345",
      "regime": "偏多震盪",
      "rank": 14
    },
    {
      "score": 64.22,
      "pvo": -3.84,
      "vri": 58.5,
      "slope_z": 0.92,
      "slope": 8.864,
      "action": "觀察",
      "signal": "基準-持有",
      "combo_key": "基準-持有",
      "close": 393.0,
      "atr": 19.17,
      "pos_weight": 0.13,
      "symbol": "3711",
      "regime": "偏多震盪",
      "rank": 15
    },
    {
      "score": 63.6,
      "pvo": -15.5,
      "vri": 54.8,
      "slope_z": 1.28,
      "slope": 4.85,
      "action": "觀察",
      "signal": "基準-強勢",
      "combo_key": "基準-強勢",
      "close": 508.0,
      "atr": 12.64,
      "pos_weight": 0.15,
      "symbol": "2379",
      "regime": "偏多震盪",
      "rank": 16
    },
    {
      "score": 63.28,
      "pvo": -16.2,
      "vri": 52.0,
      "slope_z": 1.27,
      "slope": 5.479,
      "action": "觀察",
      "signal": "基準-強勢-縮量",
      "combo_key": "基準-強勢",
      "close": 2310.0,
      "atr": 75.44,
      "pos_weight": 0.12,
      "symbol": "3008",
      "regime": "偏多震盪",
      "rank": 17
    },
    {
      "score": 62.0,
      "pvo": -12.73,
      "vri": 47.3,
      "slope_z": 0.98,
      "slope": 6.14,
      "action": "觀察",
      "signal": "基準-持有",
      "combo_key": "基準-持有",
      "close": 3630.0,
      "atr": 156.12,
      "pos_weight": 0.13,
      "symbol": "6669",
      "regime": "偏多震盪",
      "rank": 18
    },
    {
      "score": 61.83,
      "pvo": -10.57,
      "vri": 48.2,
      "slope_z": 0.87,
      "slope": 3.46,
      "action": "觀察",
      "signal": "基準-持有",
      "combo_key": "基準-持有",
      "close": 149.5,
      "atr": 5.97,
      "pos_weight": 0.13,
      "symbol": "3035",
      "regime": "偏多震盪",
      "rank": 19
    },
    {
      "score": 61.12,
      "pvo": 9.94,
      "vri": 59.5,
      "slope_z": -0.23,
      "slope": 3.813,
      "action": "觀察",
      "signal": "基準-持有",
      "combo_key": "基準-持有",
      "close": 95.3,
      "atr": 7.04,
      "pos_weight": 0.13,
      "symbol": "8096",
      "regime": "偏多震盪",
      "rank": 20
    }
  ],
  "pool_mu": 66.95,
  "pool_sigma": 11.54,
  "win_rate": 57.1,
  "regime": "偏多震盪",
  "total_scored": 29,
  "skipped": 0,
  "generated_at": "2026-04-12 13:48",
  "date": "2026-04-12"
}